conplex_dti/MAIN_OLD.txt
conplex_dti/__init__.py
conplex_dti/__main__.py
conplex_dti/architectures.py
conplex_dti/cli/__init__.py
conplex_dti/cli/download.py
conplex_dti/cli/predict.py
conplex_dti/cli/train.py
conplex_dti/dataset/__init__.py
conplex_dti/dataset/datamodules.py
conplex_dti/featurizer/__init__.py
conplex_dti/featurizer/base.py
conplex_dti/featurizer/molecule.py
conplex_dti/featurizer/protein.py
conplex_dti/model/__init__.py
conplex_dti/model/architectures.py
conplex_dti/model/margin.py
conplex_dti/utils.py
conplex_dti-0.1.12.dist-info/LICENSE
conplex_dti-0.1.12.dist-info/METADATA
conplex_dti-0.1.12.dist-info/WHEEL
conplex_dti-0.1.12.dist-info/entry_points.txt
conplex_dti-0.1.12.dist-info/RECORD
